fti/__init__.py
fti/file_type_getters/__init__.py
fti/file_type_getters/get_by_content_disposition.py
fti/file_type_getters/get_by_content_header.py
fti/file_type_getters/get_by_mimetype.py
fti/file_type_getters/get_by_url.py
fti/file_types.py
fti/getters.py
file_type_identifier-0.2.4.dist-info/METADATA
file_type_identifier-0.2.4.dist-info/WHEEL
file_type_identifier-0.2.4.dist-info/RECORD
