Metadata-Version: 2.3
Name: file-type-identifier
Version: 0.2.4
Summary: Library for identifying file type
License: MIT
Author: Kurbanov Bulat
Author-email: b.kurbanov@speechki.org
Requires-Python: >=3.9,<4.0
Classifier: License :: OSI Approved :: MIT License
Classifier: Programming Language :: Python :: 3
Classifier: Programming Language :: Python :: 3.9
Classifier: Programming Language :: Python :: 3.10
Classifier: Programming Language :: Python :: 3.11
Classifier: Programming Language :: Python :: 3.12
Classifier: Programming Language :: Python :: 3.13
Requires-Dist: httpx
